digup/__init__.py
digup/aggregation.py
digup/cli.py
digup/colorize.py
digup/commands.py
digup/count_words.py
digup/get_nodes.py
digup/highlight.py
digup/limits.py
digup/present.py
digup-0.0.8.dist-info/METADATA
digup-0.0.8.dist-info/WHEEL
digup-0.0.8.dist-info/entry_points.txt
digup-0.0.8.dist-info/licenses/LICENSE
digup-0.0.8.dist-info/RECORD
