Metadata-Version: 2.4
Name: digup
Version: 0.0.8
Summary: Your cli buddy to dig up knowledge from legacy code
Author: Alexandre Petit
License-Expression: MIT
License-File: LICENSE
Classifier: Operating System :: OS Independent
Classifier: Programming Language :: Python :: 3
Requires-Python: >=3.12
